json_flattener/__init__.py
json_flattener/cli.py
json_flattener/flattener.py
json_flattener-0.1.9.dist-info/LICENSE
json_flattener-0.1.9.dist-info/METADATA
json_flattener-0.1.9.dist-info/WHEEL
json_flattener-0.1.9.dist-info/entry_points.txt
json_flattener-0.1.9.dist-info/top_level.txt
json_flattener-0.1.9.dist-info/RECORD
