Metadata-Version: 2.1
Name: json-flattener
Version: 0.1.9
Summary: Python library for denormalizing nested dicts or json objects to tables and back
Home-page: https://github.com/cmungall/json-flattener
Author: Chris Mungall
Author-email: cjmungall@lbl.gov
License: BSD
Keywords: linkml data-science denormalization yaml json data-frames
Platform: UNKNOWN
Classifier: Intended Audience :: Science/Research
Classifier: Topic :: Scientific/Engineering :: Bio-Informatics
Classifier: License :: OSI Approved :: BSD License
Classifier: Programming Language :: Python :: 3
Requires-Python: >=3.7.0
